riseact/__init__.py
riseact/cli.py
riseact/client.py
riseact/conf.py
riseact/ui.py
riseact/topics/app/__init__.py
riseact/topics/app/commands.py
riseact/topics/app/data.py
riseact/topics/app/selectors.py
riseact/topics/app/services.py
riseact/topics/auth/__init__.py
riseact/topics/auth/commands.py
riseact/topics/auth/data.py
riseact/topics/auth/services.py
riseact/topics/info/__init__.py
riseact/topics/info/commands.py
riseact/topics/info/data.py
riseact/topics/info/selectors.py
riseact/topics/ngrok/__init__.py
riseact/topics/ngrok/commands.py
riseact/topics/settings/__init__.py
riseact/topics/settings/commands.py
riseact/topics/settings/data.py
riseact/topics/settings/selectors.py
riseact/topics/settings/services.py
riseact/topics/theme/commands.py
riseact/topics/theme/consts.py
riseact/topics/theme/data.py
riseact/topics/theme/observer.py
riseact/topics/theme/remote.py
riseact/topics/theme/services.py
riseact/topics/theme/validators.py
riseact-1.0.2.dist-info/entry_points.txt
riseact-1.0.2.dist-info/LICENSE
riseact-1.0.2.dist-info/WHEEL
riseact-1.0.2.dist-info/METADATA
riseact-1.0.2.dist-info/RECORD
